{
  "openapi": "3.0.1",
  "info": {
    "title": "MapWebAPI",
    "version": "1.0"
  },
  "paths": {
    "/api/Locations": {
      "get": {
        "tags": [
          "Locations"
        ],
        "responses": {
          "200": {
            "description": "Success",
            "content": {
              "text/plain": {
                "schema": {
                  "type": "array",
                  "items": {
                    "$ref": "#/components/schemas/LocationDto"
                  }
                }
              },
              "application/json": {
                "schema": {
                  "type": "array",
                  "items": {
                    "$ref": "#/components/schemas/LocationDto"
                  }
                }
              },
              "text/json": {
                "schema": {
                  "type": "array",
                  "items": {
                    "$ref": "#/components/schemas/LocationDto"
                  }
                }
              }
            }
          }
        }
      }
    },
    "/api/Locations/GetLocationTypes": {
      "get": {
        "tags": [
          "Locations"
        ],
        "responses": {
          "200": {
            "description": "Success",
            "content": {
              "text/plain": {
                "schema": {
                  "type": "array",
                  "items": {
                    "$ref": "#/components/schemas/LocationTypesDto"
                  }
                }
              },
              "application/json": {
                "schema": {
                  "type": "array",
                  "items": {
                    "$ref": "#/components/schemas/LocationTypesDto"
                  }
                }
              },
              "text/json": {
                "schema": {
                  "type": "array",
                  "items": {
                    "$ref": "#/components/schemas/LocationTypesDto"
                  }
                }
              }
            }
          }
        }
      }
    },
    "/api/Locations/GetLocationById/{id}": {
      "get": {
        "tags": [
          "Locations"
        ],
        "parameters": [
          {
            "name": "id",
            "in": "path",
            "required": true,
            "schema": {
              "type": "integer",
              "format": "int32"
            }
          }
        ],
        "responses": {
          "200": {
            "description": "Success",
            "content": {
              "text/plain": {
                "schema": {
                  "$ref": "#/components/schemas/Location"
                }
              },
              "application/json": {
                "schema": {
                  "$ref": "#/components/schemas/Location"
                }
              },
              "text/json": {
                "schema": {
                  "$ref": "#/components/schemas/Location"
                }
              }
            }
          }
        }
      }
    },
    "/api/Locations/AddLocation": {
      "post": {
        "tags": [
          "Locations"
        ],
        "requestBody": {
          "content": {
            "application/json": {
              "schema": {
                "$ref": "#/components/schemas/Location"
              }
            },
            "text/json": {
              "schema": {
                "$ref": "#/components/schemas/Location"
              }
            },
            "application/*+json": {
              "schema": {
                "$ref": "#/components/schemas/Location"
              }
            }
          }
        },
        "responses": {
          "200": {
            "description": "Success",
            "content": {
              "text/plain": {
                "schema": {
                  "$ref": "#/components/schemas/Location"
                }
              },
              "application/json": {
                "schema": {
                  "$ref": "#/components/schemas/Location"
                }
              },
              "text/json": {
                "schema": {
                  "$ref": "#/components/schemas/Location"
                }
              }
            }
          }
        }
      }
    },
    "/api/Locations/UpdateLocation/{id}": {
      "put": {
        "tags": [
          "Locations"
        ],
        "parameters": [
          {
            "name": "id",
            "in": "path",
            "required": true,
            "schema": {
              "type": "integer",
              "format": "int32"
            }
          }
        ],
        "requestBody": {
          "content": {
            "application/json": {
              "schema": {
                "$ref": "#/components/schemas/Location"
              }
            },
            "text/json": {
              "schema": {
                "$ref": "#/components/schemas/Location"
              }
            },
            "application/*+json": {
              "schema": {
                "$ref": "#/components/schemas/Location"
              }
            }
          }
        },
        "responses": {
          "200": {
            "description": "Success"
          }
        }
      }
    }
  },
  "components": {
    "schemas": {
      "Attribute": {
        "type": "object",
        "properties": {
          "attributeId": {
            "type": "integer",
            "format": "int32"
          },
          "locationTypeId": {
            "type": "integer",
            "format": "int32",
            "nullable": true
          },
          "name": {
            "type": "string",
            "nullable": true
          },
          "value": {
            "type": "string",
            "nullable": true
          },
          "locationType": {
            "$ref": "#/components/schemas/LocationType"
          }
        },
        "additionalProperties": false
      },
      "Location": {
        "type": "object",
        "properties": {
          "locationId": {
            "type": "integer",
            "format": "int32"
          },
          "name": {
            "type": "string",
            "nullable": true
          },
          "latitude": {
            "type": "number",
            "format": "double"
          },
          "longitude": {
            "type": "number",
            "format": "double"
          },
          "locationTypeId": {
            "type": "integer",
            "format": "int32",
            "nullable": true
          },
          "locationType": {
            "$ref": "#/components/schemas/LocationType"
          },
          "reviews": {
            "type": "array",
            "items": {
              "$ref": "#/components/schemas/Review"
            },
            "nullable": true
          }
        },
        "additionalProperties": false
      },
      "LocationAttributeDto": {
        "type": "object",
        "properties": {
          "name": {
            "type": "string",
            "nullable": true
          },
          "value": {
            "type": "string",
            "nullable": true
          }
        },
        "additionalProperties": false
      },
      "LocationDto": {
        "type": "object",
        "properties": {
          "name": {
            "type": "string",
            "nullable": true
          },
          "latitude": {
            "type": "number",
            "format": "double"
          },
          "longitude": {
            "type": "number",
            "format": "double"
          },
          "locationTypeId": {
            "type": "integer",
            "format": "int32",
            "nullable": true
          },
          "locationType": {
            "type": "string",
            "nullable": true
          },
          "iconPath": {
            "type": "string",
            "nullable": true
          },
          "reviews": {
            "type": "array",
            "items": {
              "$ref": "#/components/schemas/LocationReviewDto"
            },
            "nullable": true
          },
          "attributes": {
            "type": "array",
            "items": {
              "$ref": "#/components/schemas/LocationAttributeDto"
            },
            "nullable": true
          }
        },
        "additionalProperties": false
      },
      "LocationReviewDto": {
        "type": "object",
        "properties": {
          "userId": {
            "type": "integer",
            "format": "int32",
            "nullable": true
          },
          "rating": {
            "type": "integer",
            "format": "int32"
          },
          "comment": {
            "type": "string",
            "nullable": true
          }
        },
        "additionalProperties": false
      },
      "LocationType": {
        "type": "object",
        "properties": {
          "locationTypeId": {
            "type": "integer",
            "format": "int32"
          },
          "typeName": {
            "type": "string",
            "nullable": true
          },
          "iconPath": {
            "type": "string",
            "nullable": true
          },
          "attributes": {
            "type": "array",
            "items": {
              "$ref": "#/components/schemas/Attribute"
            },
            "nullable": true
          },
          "locations": {
            "type": "array",
            "items": {
              "$ref": "#/components/schemas/Location"
            },
            "nullable": true
          }
        },
        "additionalProperties": false
      },
      "LocationTypesDto": {
        "type": "object",
        "properties": {
          "typeName": {
            "type": "string",
            "nullable": true
          },
          "iconPath": {
            "type": "string",
            "nullable": true
          }
        },
        "additionalProperties": false
      },
      "Review": {
        "type": "object",
        "properties": {
          "reviewId": {
            "type": "integer",
            "format": "int32"
          },
          "locationId": {
            "type": "integer",
            "format": "int32",
            "nullable": true
          },
          "userId": {
            "type": "integer",
            "format": "int32",
            "nullable": true
          },
          "rating": {
            "type": "integer",
            "format": "int32"
          },
          "comment": {
            "type": "string",
            "nullable": true
          },
          "location": {
            "$ref": "#/components/schemas/Location"
          }
        },
        "additionalProperties": false
      }
    }
  }
}